{
	"cases": [{
			"id": "1",
			"title": "Radio player built in React using Sveriges Radios API:s",
			"code": "",
			"Toolbox": "",
			"More": "",
			"image": "./Images/tech.jpeg",
			"imageHero": "/Images/computer.jpg",
			"description": "Radio assignment"
		},
		{
			"id": "2",
			"title": "RadioPlayer",
			"code": "",
			"Toolbox": "",
			"More": "",
			"image": "./Images/tech.jpeg",
			"description": ""
		},
		{
			"id": "3",
			"title": "RadioPlayer",
			"code": "",
			"Toolbox": "",
			"More": "",
			"image": "./Images/tech.jpeg",
			"description": ""
		},
		{
			"id": "4",
			"title": "RadioPlayer",
			"code": "",
			"Toolbox": "",
			"More": "",
			"image": "./Images/tech.jpeg",
			"description": ""
		}
	]
}
